api66jenkins/__init__.py
api66jenkins/__version__.py
api66jenkins/artifact.py
api66jenkins/build.py
api66jenkins/credential.py
api66jenkins/exceptions.py
api66jenkins/input.py
api66jenkins/item.py
api66jenkins/job.py
api66jenkins/mix.py
api66jenkins/node.py
api66jenkins/plugin.py
api66jenkins/queue.py
api66jenkins/report.py
api66jenkins/requester.py
api66jenkins/system.py
api66jenkins/user.py
api66jenkins/view.py
api66jenkins-0.0.7.dist-info/LICENSE
api66jenkins-0.0.7.dist-info/WHEEL
api66jenkins-0.0.7.dist-info/METADATA
api66jenkins-0.0.7.dist-info/RECORD
