Metadata-Version: 2.1
Name: api66jenkins
Version: 0.0.7
Summary: Python3 client library for Jenkins API. Adding a keyword from api4jenkins  add job.build [custom] parameter
License: LICENSE
Author: sanmejie
Author-email: liyapong@foxmail.com
Requires-Python: >=3.7,<4.0
Classifier: License :: Other/Proprietary License
Classifier: Programming Language :: Python :: 3
Classifier: Programming Language :: Python :: 3.7
Classifier: Programming Language :: Python :: 3.8
Classifier: Programming Language :: Python :: 3.9
Requires-Dist: api4jenkins (>=1.12,<2.0)
Requires-Dist: requests (>=2.28.1,<3.0.0)
